nparse/__init__.py
nparse/convert.py
nparse/main.py
nparse/tmp.py
nparse-0.0.16.dist-info/LICENCE
nparse-0.0.16.dist-info/METADATA
nparse-0.0.16.dist-info/WHEEL
nparse-0.0.16.dist-info/entry_points.txt
nparse-0.0.16.dist-info/top_level.txt
nparse-0.0.16.dist-info/RECORD
