Metadata-Version: 2.1
Name: nparse
Version: 0.0.16
Summary: Notebook Parser for kaggler especially for english-learner
Home-page: https://github.com/makinzm/notebook-parser
Author: Nozomi Maki
License: MIT License
License-File: LICENCE
Requires-Dist: nbformat
